yasmine/__init__.py
yasmine/__main__.py
yasmine/train.mp3
yasmine/texte/__init__.py
yasmine/texte/texte.html
yasmine/texte/texte.odt
yasmine/texte/texte.pdf
yasmine/texte/texte.txt
yasmine-1.0.0.dist-info/METADATA
yasmine-1.0.0.dist-info/WHEEL
yasmine-1.0.0.dist-info/top_level.txt
yasmine-1.0.0.dist-info/RECORD
