Metadata-Version: 2.1
Name: yasmine
Version: 1.0.0
Summary: POÈME POUR YASMINE
Home-page: https://github.com/ghilesmeddour/yasmine
Author: Ghiles Meddour
Author-email: ghiles.meddour@munic.io
License: UNKNOWN
Project-URL: Bug Tracker, https://github.com/ghilesmeddour/yasmine/issues
Platform: UNKNOWN
Classifier: Programming Language :: Python :: 3
Classifier: Operating System :: OS Independent
Requires-Python: >=3.8
Requires-Dist: pygame
